eliv/__domain__.py
eliv/__init__.py
eliv-1.1.3.dist-info/METADATA
eliv-1.1.3.dist-info/WHEEL
eliv-1.1.3.dist-info/licenses/LICENSE
eliv-1.1.3.dist-info/RECORD
