Metadata-Version: 2.4
Name: ELIV
Version: 1.1.3
Summary: 비공식 엘리브 도메인 API Python 클라이언트
Project-URL: Repository, https://github.com/DevNergis/ELIV-Python/Domain-API.git
Project-URL: Issues, https://github.com/DevNergis/ELIV-Python/issues
Project-URL: Changelog, https://github.com/DevNergis/ELIV-Python/blob/master/CHANGELOG.md
Maintainer-email: Nergis <me@nergis.dev>
License-Expression: AGPL-3.0-or-later
License-File: LICENSE
Requires-Python: >=3.13
Requires-Dist: httpx>=0.28.1
Requires-Dist: orjson>=3.10.18
